djangoS3Browser/__init__.py
djangoS3Browser/s3_browser/__init__.py
djangoS3Browser/s3_browser/operations.py
djangoS3Browser/s3_browser/settings.py
djangoS3Browser/s3_browser/urls.py
djangoS3Browser/s3_browser/views.py
djangoS3Browser/static/css/filebrowser.css
djangoS3Browser/static/images/after-effects.png
djangoS3Browser/static/images/ai.png
djangoS3Browser/static/images/audition.png
djangoS3Browser/static/images/avi.png
djangoS3Browser/static/images/bridge.png
djangoS3Browser/static/images/css.png
djangoS3Browser/static/images/csv.png
djangoS3Browser/static/images/dbf.png
djangoS3Browser/static/images/doc.png
djangoS3Browser/static/images/dreamweaver.png
djangoS3Browser/static/images/dwg.png
djangoS3Browser/static/images/exe.png
djangoS3Browser/static/images/file.png
djangoS3Browser/static/images/fireworks.png
djangoS3Browser/static/images/fla.png
djangoS3Browser/static/images/flash.png
djangoS3Browser/static/images/folder_icon.png
djangoS3Browser/static/images/html.png
djangoS3Browser/static/images/illustrator.png
djangoS3Browser/static/images/indesign.png
djangoS3Browser/static/images/iso.png
djangoS3Browser/static/images/javascript.png
djangoS3Browser/static/images/jpg.png
djangoS3Browser/static/images/json-file.png
djangoS3Browser/static/images/mp3.png
djangoS3Browser/static/images/mp4.png
djangoS3Browser/static/images/pdf.png
djangoS3Browser/static/images/photoshop.png
djangoS3Browser/static/images/png.png
djangoS3Browser/static/images/ppt.png
djangoS3Browser/static/images/prelude.png
djangoS3Browser/static/images/premiere.png
djangoS3Browser/static/images/psd.png
djangoS3Browser/static/images/rtf.png
djangoS3Browser/static/images/search.png
djangoS3Browser/static/images/svg.png
djangoS3Browser/static/images/txt.png
djangoS3Browser/static/images/xls.png
djangoS3Browser/static/images/xml.png
djangoS3Browser/static/images/zip-1.png
djangoS3Browser/static/images/zip.png
djangoS3Browser/static/js/filebrowser.js
djangoS3Browser/templates/header.html
DjangoS3Browser-0.3.dist-info/LICENSE
DjangoS3Browser-0.3.dist-info/METADATA
DjangoS3Browser-0.3.dist-info/WHEEL
DjangoS3Browser-0.3.dist-info/top_level.txt
DjangoS3Browser-0.3.dist-info/RECORD
