Metadata-Version: 2.1
Name: DjangoS3Browser
Version: 0.3
Summary: S3 browser for django
Home-page: https://github.com/mkaykisiz/DjangoS3Browser
Author: mkaykisiz
Author-email: m.kaykisiz@gmail.com
License: MIT
Platform: UNKNOWN
License-File: LICENSE
Requires-Dist: Django (>=1.9)
Requires-Dist: boto3 (==1.4.6)
